replicate_fern/__init__.py
replicate_fern-0.0.1.dist-info/METADATA
replicate_fern-0.0.1.dist-info/WHEEL
replicate_fern-0.0.1.dist-info/top_level.txt
replicate_fern-0.0.1.dist-info/RECORD
