Metadata-Version: 2.4
Name: replicate-fern
Version: 0.0.1
Summary: Stub package to reserve the 'replicate-fern' name.
Home-page: https://github.com/yourname/replicate-fern
Author: Your Name
Author-email: you@example.com
Classifier: Programming Language :: Python :: 3
Classifier: Development Status :: 1 - Planning
Requires-Python: >=3.6
Dynamic: author
Dynamic: author-email
Dynamic: classifier
Dynamic: description
Dynamic: description-content-type
Dynamic: home-page
Dynamic: requires-python
Dynamic: summary
